locr/__init__.py
locr/constants.py
locr/exceptions.py
locr/locr.py
locr-0.4.4.dist-info/LICENSE
locr-0.4.4.dist-info/METADATA
locr-0.4.4.dist-info/WHEEL
locr-0.4.4.dist-info/top_level.txt
locr-0.4.4.dist-info/RECORD
