Metadata-Version: 2.1
Name: locr
Version: 0.4.4
Summary: Tools for fetching OCRed text of Library of Congress items.
Home-page: https://github.com/thatandromeda/locr
Author: Andromeda Yelton
License: UNKNOWN
Platform: UNKNOWN
Classifier: Programming Language :: Python :: 3
Classifier: License :: OSI Approved :: MIT License
Classifier: Operating System :: OS Independent
Requires-Python: >=3.0
License-File: LICENSE
Requires-Dist: bs4
Requires-Dist: requests
